gymbob/__init__.py
gymbob/editwin.py
gymbob/gymbob
gymbob/gymprog.py
gymbob/mainapp.py
gymbob/mainwin.py
gymbob/icons/COPYING
gymbob/icons/clock.png
gymbob/icons/clock_red.png
gymbob/icons/control_repeat_blue.png
gymbob/icons/gymbob_icon_128.png
gymbob/icons/gymbob_icon_16.png
gymbob/icons/gymbob_icon_24.png
gymbob/icons/gymbob_icon_256.png
gymbob/icons/gymbob_icon_32.png
gymbob/icons/gymbob_icon_48.png
gymbob/icons/gymbob_icon_512.png
gymbob/icons/gymbob_icon_64.png
gymbob/sounds/COPYING
gymbob/sounds/ahem.mp3
gymbob/sounds/beep.mp3
gymbob/sounds/belch.mp3
gymbob/sounds/bell.mp3
gymbob/sounds/boxing.mp3
gymbob/sounds/call.mp3
gymbob/sounds/chime.mp3
gymbob/sounds/cow.mp3
gymbob/sounds/cowbell.mp3
gymbob/sounds/cuckoo.mp3
gymbob/sounds/dixie.mp3
gymbob/sounds/doorbell.mp3
gymbob/sounds/gong.mp3
gymbob/sounds/hello.mp3
gymbob/sounds/honk.mp3
gymbob/sounds/horn.mp3
gymbob/sounds/party.mp3
gymbob/sounds/phone1.mp3
gymbob/sounds/phone2.mp3
gymbob/sounds/phone3.mp3
gymbob/sounds/phone4.mp3
gymbob/sounds/phone5.mp3
gymbob/sounds/ring.mp3
gymbob/sounds/suspense.mp3
gymbob/sounds/teaspoon.mp3
gymbob-2.6.data/scripts/gymbob
gymbob-2.6.dist-info/AUTHORS
gymbob-2.6.dist-info/LICENSE
gymbob-2.6.dist-info/METADATA
gymbob-2.6.dist-info/WHEEL
gymbob-2.6.dist-info/top_level.txt
gymbob-2.6.dist-info/RECORD
